journal_software_engineering/__init__.py
journal_software_engineering/__main__.py
journal_software_engineering/cli.py
journal_software_engineering/journal.py
journal_software_engineering-0.0.9.dist-info/AUTHORS.rst
journal_software_engineering-0.0.9.dist-info/LICENSE
journal_software_engineering-0.0.9.dist-info/METADATA
journal_software_engineering-0.0.9.dist-info/WHEEL
journal_software_engineering-0.0.9.dist-info/entry_points.txt
journal_software_engineering-0.0.9.dist-info/top_level.txt
journal_software_engineering-0.0.9.dist-info/RECORD
