Metadata-Version: 2.1
Name: journal-software-engineering
Version: 0.0.9
Summary: journal_software_engineering
Home-page: https://github.com/sagersmith8/journal_software_engineering
Author: Sage Smith
Author-email: sagersmith8@gmail.com
License: Apache Software License 2.0
Project-URL: Changelog, https://github.com/sagersmith8/journal_software_engineering/blob/master/CHANGELOG.rst
Project-URL: Issue Tracker, https://github.com/sagersmith8/journal_software_engineering/issues
Platform: UNKNOWN
Classifier: Development Status :: 5 - Production/Stable
Classifier: Intended Audience :: Developers
Classifier: License :: OSI Approved :: Apache Software License
Classifier: Operating System :: Unix
Classifier: Operating System :: POSIX
Classifier: Operating System :: Microsoft :: Windows
Classifier: Programming Language :: Python
Classifier: Programming Language :: Python :: 3.6
Classifier: Programming Language :: Python :: Implementation :: PyPy
Classifier: Topic :: Utilities
Requires-Python: >=3.6
Requires-Dist: gitpython
Requires-Dist: colorama
Requires-Dist: pandas
